{".class": "MypyFile", "_fullname": "hypothesis.strategies._internal.ipaddress", "is_partial_stub_package": false, "is_stub": false, "names": {".class": "SymbolTable", "IPv4Address": {".class": "SymbolTableNode", "cross_ref": "ipaddress.IPv4Address", "kind": "Gdef"}, "IPv4Network": {".class": "SymbolTableNode", "cross_ref": "ipaddress.IPv4Network", "kind": "Gdef"}, "IPv6Address": {".class": "SymbolTableNode", "cross_ref": "ipaddress.IPv6Address", "kind": "Gdef"}, "IPv6Network": {".class": "SymbolTableNode", "cross_ref": "ipaddress.IPv6Network", "kind": "Gdef"}, "InvalidArgument": {".class": "SymbolTableNode", "cross_ref": "hypothesis.errors.InvalidArgument", "kind": "Gdef"}, "SPECIAL_IPv4_RANGES": {".class": "SymbolTableNode", "kind": "Gdef", "node": {".class": "Var", "flags": [], "fullname": "hypothesis.strategies._internal.ipaddress.SPECIAL_IPv4_RANGES", "name": "SPECIAL_IPv4_RANGES", "type": {".class": "TupleType", "implicit": false, "items": ["builtins.str", "builtins.str", "builtins.str", "builtins.str", "builtins.str", "builtins.str", "builtins.str", "builtins.str", "builtins.str", "builtins.str", "builtins.str", "builtins.str", "builtins.str", "builtins.str", "builtins.str", "builtins.str", "builtins.str", "builtins.str", "builtins.str", "builtins.str", "builtins.str", "builtins.str", "builtins.str", "builtins.str"], "partial_fallback": {".class": "Instance", "args": [{".class": "AnyType", "missing_import_name": null, "source_any": null, "type_of_any": 6}], "type_ref": "builtins.tuple"}}}}, "SPECIAL_IPv6_RANGES": {".class": "SymbolTableNode", "kind": "Gdef", "node": {".class": "Var", "flags": [], "fullname": "hypothesis.strategies._internal.ipaddress.SPECIAL_IPv6_RANGES", "name": "SPECIAL_IPv6_RANGES", "type": {".class": "TupleType", "implicit": false, "items": ["builtins.str", "builtins.str", "builtins.str", "builtins.str", "builtins.str", "builtins.str", "builtins.str", "builtins.str", "builtins.str", "builtins.str", "builtins.str", "builtins.str", "builtins.str", "builtins.str", "builtins.str", "builtins.str", "builtins.str", "builtins.str", "builtins.str", "builtins.str"], "partial_fallback": {".class": "Instance", "args": [{".class": "AnyType", "missing_import_name": null, "source_any": null, "type_of_any": 6}], "type_ref": "builtins.tuple"}}}}, "SearchStrategy": {".class": "SymbolTableNode", "cross_ref": "hypothesis.strategies._internal.strategies.SearchStrategy", "kind": "Gdef"}, "Union": {".class": "SymbolTableNode", "cross_ref": "typing.Union", "kind": "Gdef"}, "__doc__": {".class": "SymbolTableNode", "kind": "Gdef", "node": {".class": "Var", "flags": ["is_ready"], "fullname": "hypothesis.strategies._internal.ipaddress.__doc__", "name": "__doc__", "type": "builtins.str"}}, "__file__": {".class": "SymbolTableNode", "kind": "Gdef", "node": {".class": "Var", "flags": ["is_ready"], "fullname": "hypothesis.strategies._internal.ipaddress.__file__", "name": "__file__", "type": "builtins.str"}}, "__name__": {".class": "SymbolTableNode", "kind": "Gdef", "node": {".class": "Var", "flags": ["is_ready"], "fullname": "hypothesis.strategies._internal.ipaddress.__name__", "name": "__name__", "type": "builtins.str"}}, "__package__": {".class": "SymbolTableNode", "kind": "Gdef", "node": {".class": "Var", "flags": ["is_ready"], "fullname": "hypothesis.strategies._internal.ipaddress.__package__", "name": "__package__", "type": "builtins.str"}}, "binary": {".class": "SymbolTableNode", "cross_ref": "hypothesis.strategies._internal.core.binary", "kind": "Gdef"}, "check_type": {".class": "SymbolTableNode", "cross_ref": "hypothesis.internal.validation.check_type", "kind": "Gdef"}, "defines_strategy": {".class": "SymbolTableNode", "cross_ref": "hypothesis.strategies._internal.core.defines_strategy", "kind": "Gdef"}, "integers": {".class": "SymbolTableNode", "cross_ref": "hypothesis.strategies._internal.core.integers", "kind": "Gdef"}, "ip_addresses": {".class": "SymbolTableNode", "kind": "Gdef", "node": {".class": "Decorator", "func": {".class": "FuncDef", "arg_kinds": [5, 5], "arg_names": ["v", "network"], "flags": ["is_decorated"], "fullname": "hypothesis.strategies._internal.ipaddress.ip_addresses", "name": "ip_addresses", "type": {".class": "CallableType", "arg_kinds": [5, 5], "arg_names": ["v", "network"], "arg_types": [{".class": "UnionType", "items": ["builtins.int", {".class": "NoneType"}]}, {".class": "UnionType", "items": ["builtins.str", "ipaddress.IPv4Network", "ipaddress.IPv6Network", {".class": "NoneType"}]}], "bound_args": [], "def_extras": {"first_arg": null}, "fallback": "builtins.function", "implicit": false, "is_ellipsis_args": false, "name": "ip_addresses", "ret_type": {".class": "Instance", "args": [{".class": "UnionType", "items": ["ipaddress.IPv4Address", "ipaddress.IPv6Address"]}], "type_ref": "hypothesis.strategies._internal.strategies.SearchStrategy"}, "variables": []}}, "is_overload": false, "var": {".class": "Var", "flags": ["is_ready"], "fullname": null, "name": "ip_addresses", "type": {".class": "CallableType", "arg_kinds": [5, 5], "arg_names": ["v", "network"], "arg_types": [{".class": "UnionType", "items": ["builtins.int", {".class": "NoneType"}]}, {".class": "UnionType", "items": ["builtins.str", "ipaddress.IPv4Network", "ipaddress.IPv6Network", {".class": "NoneType"}]}], "bound_args": [], "def_extras": {"first_arg": null}, "fallback": "builtins.function", "implicit": false, "is_ellipsis_args": false, "name": "ip_addresses", "ret_type": {".class": "Instance", "args": [{".class": "UnionType", "items": ["ipaddress.IPv4Address", "ipaddress.IPv6Address"]}], "type_ref": "hypothesis.strategies._internal.strategies.SearchStrategy"}, "variables": []}}}}, "ip_network": {".class": "SymbolTableNode", "cross_ref": "ipaddress.ip_network", "kind": "Gdef"}, "sampled_from": {".class": "SymbolTableNode", "cross_ref": "hypothesis.strategies._internal.core.sampled_from", "kind": "Gdef"}}, "path": "/home/orion92/.local/lib/python3.5/site-packages/hypothesis/strategies/_internal/ipaddress.py"}